LICENSE
MANIFEST.in
README.rst
setup.cfg
setup.py
django_autodemo/__init__.py
django_autodemo/apps.py
django_autodemo/settings.py
django_autodemo/signals.py
django_autodemo/urls.py
django_autodemo/views.py
django_autodemo.egg-info/PKG-INFO
django_autodemo.egg-info/SOURCES.txt
django_autodemo.egg-info/dependency_links.txt
django_autodemo.egg-info/top_level.txt
django_autodemo/tests/__init__.py
django_autodemo/tests/settings.py
django_autodemo/tests/test_integration.py
django_autodemo/tests/test_signals.py
django_autodemo/tests/urls.py
django_autodemo/tests/views.py