Metadata-Version: 1.1
Name: django-autodemo
Version: 0.1.0
Summary: Demo mode to allow arbitrary authentication on website.
Home-page: https://github.com/panchr/django-autodemo
Author: Rushy Panchal
Author-email: rpanchal@princeton.edu
License: LGPLv3
Keywords: django,authentication,demo
Platform: UNKNOWN
Classifier: Programming Language :: Python :: 2
Classifier: Programming Language :: Python :: 2.7
Classifier: Programming Language :: Python :: 3
Classifier: Programming Language :: Python :: 3.4
Classifier: Programming Language :: Python :: 3.5
Classifier: Topic :: Internet :: WWW/HTTP :: WSGI :: Middleware
Classifier: Topic :: Software Development :: Libraries :: Python Modules
Classifier: Intended Audience :: Developers
Classifier: Operating System :: OS Independent
Classifier: License :: OSI Approved :: GNU Lesser General Public License v3 (LGPLv3)
